PyGraphica
