Metadata-Version: 2.1
Name: PyGraphica
Version: 0.1.1
Summary: PyGraphica is an easy-to-learn GUI module designed for Python, built on the Python bindings (pysdl2) for SDL-2.
Home-page: https://github.com/LukeCampbell5853/PyGraphica
Author: Luke Campbell
Author-email: LukeCampbell5853@gmail.com
License: MIT
Keywords: gui
Platform: UNKNOWN
License-File: LICENSE.txt
